emotion/__init__.py
emotion/artifacts.dvc
emotion/cli/__init__.py
emotion/data/__init__.py
emotion/data/audio/__init__.py
emotion/data/audio/audio_utils.py
emotion/data/audio/label_utils.py
emotion/data/audio/split_audio_files.py
emotion/data/labels.py
emotion/features/__init__.py
emotion/features/audio/__init__.py
emotion/features/audio/extract_features.py
emotion/features/text/extract_text.py
emotion/models/__init__.py
emotion/models/audio_model.py
emotion/models/text_model.py
emotion/train/__init__.py
emotion/train/audio/__init__.py
emotion/train/audio/svc_model.py
emotion/train/text/bert_classifier.py
emotion/utils.py
emotion/visualization/__init__.py
a62_emotion-0.11.4.dist-info/entry_points.txt
a62_emotion-0.11.4.dist-info/WHEEL
a62_emotion-0.11.4.dist-info/METADATA
a62_emotion-0.11.4.dist-info/RECORD
