Metadata-Version: 2.1
Name: a62-emotion
Version: 0.11.4
Summary: A model for emotion classification based on text and audio.
Home-page: https://github.com/philipgaudreau/emotion
Author: Philip Gaudreau
Author-email: this@philipgaudreau.email
Requires-Python: ==3.8.13
Classifier: Programming Language :: Python :: 3
Requires-Dist: Flask (>=2.1.2,<3.0.0)
Requires-Dist: dvc[gdrive] (<2.11)
Requires-Dist: gunicorn (>=20.1.0,<21.0.0)
Requires-Dist: keras (>=2.8.0,<3.0.0)
Requires-Dist: librosa (>=0.9.1,<0.10.0)
Requires-Dist: nltk (>=3.7,<4.0)
Requires-Dist: numpy (==1.20.3)
Requires-Dist: pandas (==1.2.4)
Requires-Dist: scikit-learn (==0.24.2)
Requires-Dist: tensorflow-cpu (>=2.9.1,<3.0.0)
Requires-Dist: tensorflow-hub (>=0.12.0,<0.13.0)
Requires-Dist: transformers (>=4.20.1,<5.0.0)
Project-URL: Repository, https://github.com/philipgaudreau/emotion
